invenio_mail/__init__.py
invenio_mail/api.py
invenio_mail/config.py
invenio_mail/errors.py
invenio_mail/ext.py
invenio_mail/tasks.py
invenio_mail-2.3.0.dist-info/licenses/AUTHORS.rst
invenio_mail-2.3.0.dist-info/licenses/LICENSE
invenio_mail-2.3.0.dist-info/METADATA
invenio_mail-2.3.0.dist-info/WHEEL
invenio_mail-2.3.0.dist-info/entry_points.txt
invenio_mail-2.3.0.dist-info/top_level.txt
invenio_mail-2.3.0.dist-info/RECORD
