Metadata-Version: 2.4
Name: invenio-mail
Version: 2.3.0
Summary: Invenio-Mail is an integration layer between Invenio and Flask-Mail.
Home-page: https://github.com/inveniosoftware/invenio-mail
Author: CERN
Author-email: info@inveniosoftware.org
License: MIT
Keywords: invenio mail
Platform: any
Classifier: Development Status :: 5 - Production/Stable
Requires-Python: >=3.7
License-File: LICENSE
License-File: AUTHORS.rst
Requires-Dist: Flask>=0.11.1
Requires-Dist: Flask-Mail<0.10.0,>=0.9.1
Provides-Extra: tests
Requires-Dist: pytest-black-ng>=0.4.0; extra == "tests"
Requires-Dist: pytest-invenio<3.0.0,>=2.1.0; extra == "tests"
Requires-Dist: Flask-CeleryExt>=0.2.2; extra == "tests"
Requires-Dist: sphinx>=4.5.0; extra == "tests"
Provides-Extra: celery
Provides-Extra: docs
Dynamic: license-file
